MANIFEST.in
README.md
VERSION
setup.py
bin/pyquay.py
bin/quaycli.py
pyquay/__init__.py
pyquay.egg-info/PKG-INFO
pyquay.egg-info/SOURCES.txt
pyquay.egg-info/dependency_links.txt
pyquay.egg-info/top_level.txt