Metadata-Version: 1.0
Name: pyquay
Version: 0.0.3
Summary: Quay python client
Home-page: https://www.socotra.com
Author: Chris Antenesse
Author-email: chris.antenesse@socotra.com
License: all rights reserved
Platform: UNKNOWN
